imm_sel.vh
/*
    ifndef checks whether IMM_SEL has been defined, and if not, we proceed to define IMM_SEL
*/
`ifndef IMM_SEL
`define IMM_SEL

// Define instruction type, using 3 bits to represent a total of 6 instruction types (000 - I, etc.)
`define I_TYPE 3'd0
`define S_TYPE 3'd1
`define B_TYPE 3'd2
`define U_TYPE 3'd3
`define J_TYPE 3'd4

`endif

imm_gen.sv
`include "imm_sel.vh"

module imm_gen (
    // following datapath, only top 25 bits of full 32 bit instruction fed in (i.e. 32_inst[31:7])
    input wire [24:0] inst,
    input wire [2:0] imm_sel,

    output reg [31:0] out
);

    always @(*) begin
        case (imm_sel)
            `I_TYPE: out = {{21{inst[24]}}, inst[23:18], inst[17:14], inst[13]};
            `S_TYPE: out = {{21{inst[24]}}, inst[23:18], inst[4:1], inst[0]};
            `B_TYPE: out = {{20{inst[24]}}, inst[0], inst[23:18], inst[4:1], 1'b0};
            `U_TYPE: out = {inst[24], inst[23:13], inst[12:5], 12'b0};
            `J_TYPE: out = {{12{inst[24]}}, inst[12:5], inst[13], inst[23:18], inst[17:14], 1'b0};
            default: out = 32'b0; // Add default case for completeness
        endcase
    end
endmodule

tb/imm_gen_tb.sv
`include "imm_sel.vh"

module imm_gen_tb;
    logic [24:0] inst;
    logic [2:0] imm_sel;

    logic [31:0] out;

    imm_gen DUT (
        .inst       (inst),
        .imm_sel    (imm_sel),
        .out        (out)
    );

    integer i_pass = 0, i_fail = 0;
    integer s_pass = 0, s_fail = 0;
    integer b_pass = 0, b_fail = 0;
    integer u_pass = 0, u_fail = 0;
    integer j_pass = 0, j_fail = 0;
    integer total_pass = 0, total_fail = 0;

    // I-TYPE tests
    integer inst_addi_pos = 32'h00C48413;
    integer inst_addi_neg = 32'hFFC48413;
    // S-TYPE tests
    integer inst_sh_pos = 32'h00941823;
    integer inst_sh_neg = 32'hFE941E23;
    // B-TYPE tests
    integer inst_beq_pos = 32'h00A48E63;
    integer inst_beq_neg = 32'hFEA48863;
    // U-TYPE tests
    integer inst_lui = 32'h54321437;
    // J-TYPE tests
    integer inst_jal_pos = 32'h7FFFF0EF;
    integer inst_jal_neg = 32'h800000EF;

    initial begin
        $dumpfile("imm_gen_tb.vcd");
        $dumpvars(0, imm_gen_tb);

//-----------------------------------------I-TYPE------------------------------------
        // I-TYPE (postive immediate)
        // addi s0, s1, 12
        // Field Values (dec): imm[11:0] = 12, rs1 = x9, f3 = 0, rd = x8, op = 17
        // Machine Code: imm[11:0] = 0000 0000 1100, rs1 = 01001, f3 = 000, rd = 01000, op = 001 0011
        // Final 32-bit hex: 0x00C48413
        inst = inst_addi_pos[31:7]; imm_sel = `I_TYPE;
        #10;
        if (out == 32'd12) begin
            $display("PASS: Postive I_TYPE");
            i_pass++;
        end else begin
            $display("FAIL: Postive I_TYPE");
            $display("  Expected: %0d, Got: %0d", 32'd12, out);
            i_fail++;
        end
        // I-TYPE (negative immediate)
        // addi s0, s1, -4
        // Field Values (dec): imm[11:0] = -4, rs1 = x9, f3 = 0, rd = x8, op = 17
        // Machine Code: imm[11:0] = 1111 1111 1100, rs1 = 01001, f3 = 000, rd = 01000, op = 001 0011
        // Final 32-bit hex: 0xFFC48413
        inst = inst_addi_neg[31:7]; imm_sel = `I_TYPE;
        #10;
        if (out == -32'd4) begin
            $display("PASS: Negative I_TYPE");
            i_pass++;
        end else begin
            $display("FAIL: Negative I_TYPE");
            $display("  Expected: %0d, Got: %0d", $signed(-32'd4), $signed(out));
            i_fail++;
        end

//-----------------------------------------------------------------------------------

//-----------------------------------------S-TYPE------------------------------------
        // S-TYPE (positive immediate)
        // sh x9, 16(x8)
        // Field Values (dec): imm[11:5] = 0, imm[4:0] = 16, rs2 = x9, rs1 = x8, f3 = 2, op = 35
        // Machine Code: imm[11:5] = 000 0000, rs2 = 01001, rs1 = 01000, f3 = 001, imm[4:0] = 10000, op = 010 0011
        // Final 32-bit hex: 0x00941823
        inst = inst_sh_pos[31:7]; imm_sel = `S_TYPE;
        #10;
        if (out == 32'd16) begin
            $display("PASS: Postive S_TYPE");
            s_pass++;
        end else begin
            $display("FAIL: Postive S_TYPE");
            $display(" Expected: %0d, Got: %0d", 32'd16, out);
            s_fail++;
        end
        // S-TYPE (negative immediate)
        // sh x9, -4(x8)
        // Field Values (dec): imm[11:5] = 127, imm[4:0] = 28, rs2 = x9, rs1 = x8, f3 = 2, op = 35
        // Machine Code: imm[11:5] = 111 1111, rs2 = 01001, rs1 = 01000, f3 = 001, imm[4:0] = 11100, op = 010 0011
        // Final 32-bit hex: 0xFE941E23
        inst = inst_sh_neg[31:7]; imm_sel = `S_TYPE;
        #10;
        if (out == -32'd4) begin
            $display("PASS: Negative S_TYPE");
            s_pass++;
        end else begin
            $display("FAIL: Negative S_TYPE");
            $display(" Expected: %0d, Got: %0d", $signed(-32'd4), $signed(out));
            s_fail++;
        end

//-----------------------------------------------------------------------------------

//-----------------------------------------B-TYPE------------------------------------

        // B-TYPE (positive immediate)
        // beq x9, x10, 28
        // Field Values (dec): imm[12]=0, imm[10:5]=0, imm[4:1]=7, imm[11]=0, rs2=x10, rs1=x9, f3=0, op=99
        // Machine Code: imm[12,10:5]=000 0000, rs2=01010, rs1=01001, f3=000, imm[4:1,11]=0111 0, op=110 0011
        // Final 32-bit hex: 0x00A48E63
        inst = inst_beq_pos[31:7]; imm_sel = `B_TYPE;
        #10;
            if (out == 32'd28) begin
            $display("PASS: Basic B_TYPE");
            b_pass++;
        end else begin
            $display("FAIL: Basic B_TYPE");
            $display(" Expected: %0d, Got: %0d", 32'd28, out);
            b_fail++;
        end

        // B-TYPE (negative immediate)
        // beq x9, x10, -2064
        // Field Values (dec): imm[12]=1, imm[10:5]=63, imm[4:1]=4, imm[11]=0, rs2=x10, rs1=x9, f3=0, op=99
        // Machine Code: imm[12,10:5]=111 1111, rs2=01010, rs1=01001, f3=000, imm[4:1,11]=0100 0, op=110 0011
        // Final 32-bit hex: 0xFEA48863
        inst = inst_beq_neg[31:7]; imm_sel = `B_TYPE;
        #10;
        if (out == -32'd2064) begin
            $display("PASS: Negative B_TYPE");
            b_pass++;
        end else begin
            $display("FAIL: Negative B_TYPE");
            $display(" Expected: %0d, Got: %0d", $signed(-32'd2064), $signed(out));
            b_fail++;
        end

//-----------------------------------------------------------------------------------

//-----------------------------------------U-TYPE------------------------------------

        // U-TYPE
        // lui x8, 0x54321
        // 32-bit hex: 0x54321437
        inst = inst_lui[31:7]; imm_sel = `U_TYPE;
        #10;
        if (out == 32'h54321000) begin
            $display("PASS: U_TYPE");
            i_pass++;
        end else begin
            $display("FAIL: U_TYPE");
            $display(" Expected: %0h, Got: %0h", 32'h54321000, out);
            i_fail++;
        end

//-----------------------------------------------------------------------------------

//-----------------------------------------J-TYPE------------------------------------

        // J-TYPE (positive immediate)
        // jal x1, 1048574 (0xFFFFFC)
        // Field Values: imm[20]=0, imm[10:1]=0x3FF, imm[11]=0, imm[19:12]=0xFF, rd=x1, op=111
        // Machine Code: imm[20,10:1,11,19:12]=0 11 1111 1111 0 1111 1111, rd=00001, op=110 1111
        // Final 32-bit hex: 0x7FFFF0EF
        inst = inst_jal_pos[31:7]; imm_sel = `J_TYPE;
        #10;
        if (out == 32'd1048574) begin
            $display("PASS: Positive J_TYPE");
            j_pass++;
        end else begin
            $display("FAIL: Positive J_TYPE");
            $display(" Expected: %0d, Got: %0d", 32'd1048574, out);
            j_fail++;
        end

        // J-TYPE (negative immediate)
        // jal x1, -1048576 (0xFFF00000)
        // Field Values: imm[20]=1, imm[10:1]=0x000, imm[11]=0, imm[19:12]=0x00, rd=x1, op=111
        // Machine Code: imm[20,10:1,11,19:12]=1 00 0000 0000 0 0000 0000, rd=00001, op=110 1111
        // Final 32-bit hex: 0x800000EF
        inst = inst_jal_neg[31:7]; imm_sel = `J_TYPE;
        #10;
        if (out == -32'd1048576) begin
            $display("PASS: Negative J_TYPE");
            j_pass++;
        end else begin
            $display("FAIL: Negative J_TYPE");
            $display(" Expected: %0d, Got: %0d", $signed(-32'd1048576), $signed(out));
            j_fail++;
        end

//-----------------------------------------------------------------------------------
        total_pass = i_pass + s_pass + b_pass + u_pass + j_pass;
        total_fail = i_fail + s_fail + b_fail + u_fail + j_fail;
        $display("SUMMARY: %d passed, %d failed", total_pass, total_fail);

        $finish;
    end
endmodule

sim/waves/imm_gen_tb.vcd
$date
	Thu Mar  6 00:21:08 2025
$end
$version
	Icarus Verilog
$end
$timescale
	1s
$end
$scope module imm_gen_tb $end
$var wire 32 ! out [31:0] $end
$var reg 3 " imm_sel [2:0] $end
$var reg 25 # inst [24:0] $end
$var integer 32 $ b_fail [31:0] $end
$var integer 32 % b_pass [31:0] $end
$var integer 32 & i_fail [31:0] $end
$var integer 32 ' i_pass [31:0] $end
$var integer 32 ( inst_addi_neg [31:0] $end
$var integer 32 ) inst_addi_pos [31:0] $end
$var integer 32 * inst_beq_neg [31:0] $end
$var integer 32 + inst_beq_pos [31:0] $end
$var integer 32 , inst_jal_neg [31:0] $end
$var integer 32 - inst_jal_pos [31:0] $end
$var integer 32 . inst_lui [31:0] $end
$var integer 32 / inst_sh_neg [31:0] $end
$var integer 32 0 inst_sh_pos [31:0] $end
$var integer 32 1 j_fail [31:0] $end
$var integer 32 2 j_pass [31:0] $end
$var integer 32 3 s_fail [31:0] $end
$var integer 32 4 s_pass [31:0] $end
$var integer 32 5 total_fail [31:0] $end
$var integer 32 6 total_pass [31:0] $end
$var integer 32 7 u_fail [31:0] $end
$var integer 32 8 u_pass [31:0] $end
$scope module DUT $end
$var wire 3 9 imm_sel [2:0] $end
$var wire 25 : inst [24:0] $end
$var reg 32 ; out [31:0] $end
$upscope $end
$upscope $end
$enddefinitions $end
$comment Show the parameter values. $end
$dumpall
$end
#0
$dumpvars
b1100 ;
b11000100100001000 :
b0 9
b0 8
b0 7
b0 6
b0 5
b0 4
b0 3
b0 2
b0 1
b100101000001100000100011 0
b11111110100101000001111000100011 /
b1010100001100100001010000110111 .
b1111111111111111111000011101111 -
b10000000000000000000000011101111 ,
b101001001000111001100011 +
b11111110101001001000100001100011 *
b110001001000010000010011 )
b11111111110001001000010000010011 (
b0 '
b0 &
b0 %
b0 $
b11000100100001000 #
b0 "
b1100 !
$end
#10
b11111111111111111111111111111100 !
b11111111111111111111111111111100 ;
b1111111111000100100001000 #
b1111111111000100100001000 :
b1 '
#20
b10000 !
b10000 ;
b1 "
b1 9
b10010100000110000 #
b10010100000110000 :
b10 '
#30
b11111111111111111111111111111100 !
b11111111111111111111111111111100 ;
b1111111010010100000111100 #
b1111111010010100000111100 :
b1 4
#40
b11100 !
b11100 ;
b10 "
b10 9
b10100100100011100 #
b10100100100011100 :
b10 4
#50
b11111111111111111111011111110000 !
b11111111111111111111011111110000 ;
b1111111010100100100010000 #
b1111111010100100100010000 :
b1 %
#60
b1010100001100100001000000000000 !
b1010100001100100001000000000000 ;
b11 "
b11 9
b101010000110010000101000 #
b101010000110010000101000 :
b10 %
#70
b11111111111111111110 !
b11111111111111111110 ;
b100 "
b100 9
b111111111111111111100001 #
b111111111111111111100001 :
b11 '
#80
b11111111111100000000000000000000 !
b11111111111100000000000000000000 ;
b1000000000000000000000001 #
b1000000000000000000000001 :
b1 2
#90
b1001 6
b10 2
